MANIFEST.in
README.md
requirements.txt
setup.py
ipflakies/__main__.py
ipflakies/detector.py
ipflakies/idflakies.py
ipflakies/initializers.py
ipflakies/main.py
ipflakies/patcher.py
ipflakies/randomizer.py
ipflakies/unparse.py
ipflakies/utils.py
ipflakies.egg-info/PKG-INFO
ipflakies.egg-info/SOURCES.txt
ipflakies.egg-info/dependency_links.txt
ipflakies.egg-info/requires.txt
ipflakies.egg-info/top_level.txt