Metadata-Version: 1.0
Name: ipflakies
Version: 1.1.1
Summary: A tool for automatically detecting and fixing OD tests.
Home-page: https://github.com/ailen-wrx/python-ipflakies
Author: Ruixin Wang, Yang Chen
Author-email: wangrx1999@outlook.com, sunniercy@gmial.com
License: MIT Licence
Keywords: pip,flaky_test,flaky
Platform: Linux
Platform: MacOS
